talk2stat/__init__.py
talk2stat/talk2stat.py
talk2stat-0.1.7.dist-info/LICENSE
talk2stat-0.1.7.dist-info/METADATA
talk2stat-0.1.7.dist-info/WHEEL
talk2stat-0.1.7.dist-info/top_level.txt
talk2stat-0.1.7.dist-info/RECORD
