Metadata-Version: 2.1
Name: talk2stat
Version: 0.1.7
Summary: Open a bidirectional pipe to R, julia, matlab, or python (etc.) and communicate with it via a socket.
Home-page: https://pypi.org/project/talk2stat/
Author: Haim Bar
Author-email: haim.bar@uconn.edu
License: UNKNOWN
Platform: UNKNOWN
Classifier: Programming Language :: Python :: 3
Classifier: License :: OSI Approved :: MIT License
Classifier: Operating System :: OS Independent
License-File: LICENSE
Requires-Dist: pexpect
